[
  {
    "listing": "/学汉语的日记.html",
    "items": [
      "/学汉语的日记/HSK5下-第32课-身边的环保/index.html",
      "/学汉语的日记/HSK5下-第31课-登门槛效应/index.html",
      "/学汉语的日记/2024-06-03_hskk-langdu-wuxiaxiaoshuo/index.html",
      "/学汉语的日记/2024-06-02_hskk-langdu-beijing/index.html",
      "/学汉语的日记/HSK5下-第30课-竞争让市场更高效/index.html",
      "/学汉语的日记/HSK5下-第29课-培养对手/index.html",
      "/学汉语的日记/HSK5下-第36课-老舍与养花/index.html",
      "/学汉语的日记/HSK5下-第35课-植物会出汗/index.html",
      "/学汉语的日记/HSK5下-第34课-鸟儿的护肤术/index.html",
      "/学汉语的日记/HSK5下-第33课-以堵治堵-缓解交通有妙招/index.html",
      "/学汉语的日记/HSK5下-第28课-最受欢迎的毕业生/index.html",
      "/学汉语的日记/HSK5下-第27课-下棋/index.html",
      "/学汉语的日记/HSK5下-第26课-你属于哪种忙/index.html",
      "/学汉语的日记/HSK5下-第25课-给自己加满水/index.html",
      "/学汉语的日记/HSK5下-第24课-支教行动/index.html",
      "/学汉语的日记/HSK5下-第23课-放手/index.html",
      "/学汉语的日记/HSK5下-第22课-阅读与思考/index.html",
      "/学汉语的日记/HSK5下-第21课-汉字叔叔 - 一个美国人的汉字情缘/index.html",
      "/学汉语的日记/HSK5下-第20课-小人书摊/index.html",
      "/学汉语的日记/HSK5下-第19课-家乡的萝卜饼/index.html",
      "/学汉语的日记/HSK5上-第18课-抽象艺术美不美/index.html",
      "/学汉语的日记/HSK5上-第17课-在最美好的时刻离开/index.html",
      "/学汉语的日记/HSK5上-第16课-体重与节食/index.html",
      "/学汉语的日记/HSK5上-第15课-纸上谈兵/index.html",
      "/学汉语的日记/HSK5上-第14课-北京的四合院/index.html",
      "/学汉语的日记/HSK5上-第13课-据掉生活的筐底/index.html",
      "/学汉语的日记/HSK5上-第12课-外国用户玩儿微信/index.html",
      "/学汉语的日记/HSK5上-第11课-闹钟的危害/index.html",
      "/学汉语的日记/HSK5上-第10课-争论的奇迹/index.html",
      "/学汉语的日记/HSK5上-第09课-别样鲁迅/index.html",
      "/学汉语的日记/HSK5上-第08课-朝三暮四/index.html",
      "/学汉语的日记/HSK5上-第07课-成语故事两则/index.html",
      "/学汉语的日记/HSK5上-第06课-除夕的由来/index.html",
      "/学汉语的日记/HSK5上-第05课-济南的泉水/index.html",
      "/学汉语的日记/HSK5上-第04课-子路背米/index.html",
      "/学汉语的日记/HSK5上-第03课-一生有选择，一切可改变/index.html",
      "/学汉语的日记/HSK5上-第02课-留串钥匙给父母/index.html",
      "/学汉语的日记/HSK5上-第01课-爱的细节/index.html"
    ]
  },
  {
    "listing": "/blog.html",
    "items": [
      "/blog/2024-06-10-python-bitcoin/index.html",
      "/blog/2024-06-19-observable/index.html",
      "/blog/2024-06-17-nn-z2h-p1/index.html",
      "/blog/2024-06-06-excel-blambda/index.html",
      "/blog/2024-06-05-cnac/index.html",
      "/blog/2024-05-22-swd-p2-improve-table/index.html",
      "/blog/2024-05-21-python-is-cool/index.html",
      "/blog/2024-04-19-qej-1/index.html",
      "/blog/2024-02-28-bjj/index.html",
      "/blog/2024-01-19-guitar-tablature/index.html",
      "/blog/2023-12-24-a-first-lession-on-ggplot2/index.html"
    ]
  },
  {
    "listing": "/index.html",
    "items": [
      "/blog/2024-06-10-python-bitcoin/index.html",
      "/blog/2024-06-19-observable/index.html",
      "/blog/2024-06-17-nn-z2h-p1/index.html",
      "/blog/2024-06-06-excel-blambda/index.html",
      "/blog/2024-06-05-cnac/index.html",
      "/blog/2024-05-22-swd-p2-improve-table/index.html",
      "/blog/2024-05-21-python-is-cool/index.html",
      "/blog/2024-04-19-qej-1/index.html",
      "/blog/2024-02-28-bjj/index.html",
      "/blog/2024-01-19-guitar-tablature/index.html",
      "/blog/2023-12-24-a-first-lession-on-ggplot2/index.html",
      "/学汉语的日记/HSK5下-第32课-身边的环保/index.html",
      "/学汉语的日记/HSK5下-第31课-登门槛效应/index.html",
      "/学汉语的日记/2024-06-02_hskk-langdu-beijing/index.html",
      "/学汉语的日记/2024-06-03_hskk-langdu-wuxiaxiaoshuo/index.html",
      "/学汉语的日记/HSK5下-第30课-竞争让市场更高效/index.html",
      "/学汉语的日记/HSK5下-第29课-培养对手/index.html",
      "/学汉语的日记/HSK5下-第21课-汉字叔叔 - 一个美国人的汉字情缘/index.html",
      "/学汉语的日记/HSK5下-第22课-阅读与思考/index.html",
      "/学汉语的日记/HSK5下-第23课-放手/index.html",
      "/学汉语的日记/HSK5下-第24课-支教行动/index.html",
      "/学汉语的日记/HSK5下-第25课-给自己加满水/index.html",
      "/学汉语的日记/HSK5下-第26课-你属于哪种忙/index.html",
      "/学汉语的日记/HSK5下-第27课-下棋/index.html",
      "/学汉语的日记/HSK5下-第28课-最受欢迎的毕业生/index.html",
      "/学汉语的日记/HSK5下-第33课-以堵治堵-缓解交通有妙招/index.html",
      "/学汉语的日记/HSK5下-第34课-鸟儿的护肤术/index.html",
      "/学汉语的日记/HSK5下-第35课-植物会出汗/index.html",
      "/学汉语的日记/HSK5下-第36课-老舍与养花/index.html",
      "/学汉语的日记/HSK5下-第20课-小人书摊/index.html",
      "/学汉语的日记/HSK5下-第19课-家乡的萝卜饼/index.html",
      "/学汉语的日记/HSK5上-第01课-爱的细节/index.html",
      "/学汉语的日记/HSK5上-第02课-留串钥匙给父母/index.html",
      "/学汉语的日记/HSK5上-第03课-一生有选择，一切可改变/index.html",
      "/学汉语的日记/HSK5上-第04课-子路背米/index.html",
      "/学汉语的日记/HSK5上-第05课-济南的泉水/index.html",
      "/学汉语的日记/HSK5上-第06课-除夕的由来/index.html",
      "/学汉语的日记/HSK5上-第07课-成语故事两则/index.html",
      "/学汉语的日记/HSK5上-第08课-朝三暮四/index.html",
      "/学汉语的日记/HSK5上-第09课-别样鲁迅/index.html",
      "/学汉语的日记/HSK5上-第10课-争论的奇迹/index.html",
      "/学汉语的日记/HSK5上-第11课-闹钟的危害/index.html",
      "/学汉语的日记/HSK5上-第12课-外国用户玩儿微信/index.html",
      "/学汉语的日记/HSK5上-第13课-据掉生活的筐底/index.html",
      "/学汉语的日记/HSK5上-第14课-北京的四合院/index.html",
      "/学汉语的日记/HSK5上-第15课-纸上谈兵/index.html",
      "/学汉语的日记/HSK5上-第16课-体重与节食/index.html",
      "/学汉语的日记/HSK5上-第17课-在最美好的时刻离开/index.html",
      "/学汉语的日记/HSK5上-第18课-抽象艺术美不美/index.html"
    ]
  }
]